madoop/__init__.py
madoop/__main__.py
madoop/exceptions.py
madoop/mapreduce.py
madoop/example/map.py
madoop/example/reduce.py
madoop/example/input/input01.txt
madoop/example/input/input02.txt
madoop-1.3.1.dist-info/licenses/LICENSE
madoop-1.3.1.dist-info/METADATA
madoop-1.3.1.dist-info/WHEEL
madoop-1.3.1.dist-info/entry_points.txt
madoop-1.3.1.dist-info/top_level.txt
madoop-1.3.1.dist-info/RECORD
