Metadata-Version: 2.4
Name: madoop
Version: 1.3.1
Summary: A light weight MapReduce framework for education.
Author-email: Andrew DeOrio <awdeorio@umich.edu>
License: MIT License
Project-URL: repository, https://github.com/eecs485staff/madoop/
Project-URL: documentation, https://github.com/eecs485staff/madoop/blob/develop/README_Hadoop_Streaming.md#hadoop-streaming-in-python
Keywords: madoop,Hadoop,MapReduce,Michigan Hadoop,Hadoop Streaming
Requires-Python: >=3.6
License-File: LICENSE
Provides-Extra: dev
Requires-Dist: build; extra == "dev"
Requires-Dist: check-manifest; extra == "dev"
Requires-Dist: pycodestyle; extra == "dev"
Requires-Dist: pydocstyle; extra == "dev"
Requires-Dist: pylint; extra == "dev"
Requires-Dist: pytest; extra == "dev"
Requires-Dist: pytest-cov; extra == "dev"
Requires-Dist: tox; extra == "dev"
Requires-Dist: twine; extra == "dev"
Dynamic: license-file
